atd_email_util_dev-0.0.2.dist-info/DESCRIPTION.rst
atd_email_util_dev-0.0.2.dist-info/METADATA
atd_email_util_dev-0.0.2.dist-info/RECORD
atd_email_util_dev-0.0.2.dist-info/WHEEL
atd_email_util_dev-0.0.2.dist-info/metadata.json
atd_email_util_dev-0.0.2.dist-info/top_level.txt
emailutil/__init__.py
emailutil/emailutil.py
