Metadata-Version: 2.0
Name: atd-email-util-dev
Version: 0.0.2
Summary: Python utilities for sending emails with a gmail account.
Home-page: https://github.com/cityofaustin/atd-data-utilities/tree/master/emailutil
Author: City of Austin
Author-email: transportation.data@austintexas.gov
License: UNKNOWN
Platform: UNKNOWN
Classifier: Programming Language :: Python :: 3
Classifier: License :: Public Domain
Classifier: Operating System :: OS Independent
Classifier: Development Status :: 4 - Beta
Requires-Dist: yagmail
